{
  "images": {
    "filename": "Video_29_image_2_image_00009.jpg",
    "image_Id": 1931,
    "width": 2880,
    "height": 2160
  },
  "persons": [
    {
      "image_Id": 1931,
      "person_id": "student",
      "person_bbox": [
        637.5,
        1676.6,
        830.2,
        1904.3
      ],
      "pose_id": "lower the head",
      "action_id": [
        "read"
      ],
      "gaze_object": {
        "gaze_object_id": "book",
        "gaze_bbox": [
          665.9,
          1843.1,
          737.7,
          1889.4
        ]
      }
    },
    {
      "image_Id": 1931,
      "person_id": "student",
      "person_bbox": [
        1070.3,
        1692.5,
        1327.1,
        1977.7
      ],
      "pose_id": "lower the head",
      "action_id": [
        "read"
      ],
      "gaze_object": {
        "gaze_object_id": "book",
        "gaze_bbox": [
          1156.4,
          1916.6,
          1300.1,
          1982.7
        ]
      }
    },
    {
      "image_Id": 1931,
      "person_id": "student",
      "person_bbox": [
        1767.5,
        1433.9,
        1903.5,
        1594
      ],
      "pose_id": "lower the head",
      "action_id": [
        "read"
      ],
      "gaze_object": {
        "gaze_object_id": "book",
        "gaze_bbox": [
          1826.3,
          1572.1,
          1894.8,
          1601.2
        ]
      }
    },
    {
      "image_Id": 1931,
      "person_id": "student",
      "person_bbox": [
        2161.2,
        1463.1,
        2266.3,
        1637.4
      ],
      "pose_id": "lower the head",
      "action_id": [
        "read"
      ],
      "gaze_object": {
        "gaze_object_id": "book",
        "gaze_bbox": [
          2208.6,
          1609.5,
          2277.9,
          1637.9
        ]
      }
    },
    {
      "image_Id": 1931,
      "person_id": "student",
      "person_bbox": [
        2368.9,
        1579.9,
        2569.9,
        1800.9
      ],
      "pose_id": "lower the head",
      "action_id": [
        "read"
      ],
      "gaze_object": {
        "gaze_object_id": "book",
        "gaze_bbox": [
          2444.8,
          1757.7,
          2550.1,
          1812.4
        ]
      }
    },
    {
      "image_Id": 1931,
      "person_id": "student",
      "person_bbox": [
        2027.4,
        1488.6,
        2147.1,
        1663.8
      ],
      "pose_id": "lower the head",
      "action_id": [
        "play phone"
      ],
      "gaze_object": {
        "gaze_object_id": "phone",
        "gaze_bbox": [
          2103.3,
          1632.3,
          2123.4,
          1653.6
        ]
      }
    },
    {
      "image_Id": 1931,
      "person_id": "student",
      "person_bbox": [
        1158.7,
        1667.6,
        1342.1,
        1827.3
      ],
      "pose_id": "lower the head",
      "action_id": [
        "sleep"
      ],
      "gaze_object": {}
    },
    {
      "image_Id": 1931,
      "person_id": "student",
      "person_bbox": [
        776.5,
        1506,
        901.8,
        1767.8
      ],
      "pose_id": "turn aside",
      "action_id": [
        "look blackboard"
      ],
      "gaze_object": {
        "gaze_object_id": "blackboard",
        "gaze_bbox": []
      }
    },
    {
      "image_Id": 1931,
      "person_id": "student",
      "person_bbox": [
        830.1,
        1673.6,
        1008.1,
        1936.3
      ],
      "pose_id": "turn aside",
      "action_id": [
        "look blackboard"
      ],
      "gaze_object": {
        "gaze_object_id": "blackboard",
        "gaze_bbox": []
      }
    },
    {
      "image_Id": 1931,
      "person_id": "student",
      "person_bbox": [
        929.2,
        1551.3,
        1060.5,
        1787.1
      ],
      "pose_id": "turn aside",
      "action_id": [
        "look blackboard"
      ],
      "gaze_object": {
        "gaze_object_id": "blackboard",
        "gaze_bbox": []
      }
    },
    {
      "image_Id": 1931,
      "person_id": "student",
      "person_bbox": [
        1253.6,
        1447.7,
        1364.8,
        1622.4
      ],
      "pose_id": "turn aside",
      "action_id": [
        "look blackboard"
      ],
      "gaze_object": {
        "gaze_object_id": "blackboard",
        "gaze_bbox": []
      }
    },
    {
      "image_Id": 1931,
      "person_id": "student",
      "person_bbox": [
        1065.5,
        1424.2,
        1165.8,
        1615.7
      ],
      "pose_id": "turn aside",
      "action_id": [
        "distracted"
      ],
      "gaze_object": {
        "gaze_object_id": "unknown",
        "gaze_bbox": []
      }
    },
    {
      "image_Id": 1931,
      "person_id": "student",
      "person_bbox": [
        991.2,
        1506.2,
        1112.9,
        1688.3
      ],
      "pose_id": "lift the head",
      "action_id": [
        "look blackboard"
      ],
      "gaze_object": {
        "gaze_object_id": "blackboard",
        "gaze_bbox": []
      }
    },
    {
      "image_Id": 1931,
      "person_id": "student",
      "person_bbox": [
        1143.1,
        1532.3,
        1308.6,
        1703.4
      ],
      "pose_id": "lower the head",
      "action_id": [
        "small action"
      ],
      "gaze_object": {
        "gaze_object_id": "unknown",
        "gaze_bbox": []
      }
    },
    {
      "image_Id": 1931,
      "person_id": "student",
      "person_bbox": [
        1553.8,
        1495.4,
        1691.3,
        1707.4
      ],
      "pose_id": "turn aside",
      "action_id": [
        "look blackboard"
      ],
      "gaze_object": {
        "gaze_object_id": "blackboard",
        "gaze_bbox": []
      }
    },
    {
      "image_Id": 1931,
      "person_id": "student",
      "person_bbox": [
        1864.1,
        1522.6,
        2023.3,
        1788.7
      ],
      "pose_id": "turn aside",
      "action_id": [
        "look blackboard"
      ],
      "gaze_object": {
        "gaze_object_id": "blackboard",
        "gaze_bbox": []
      }
    },
    {
      "image_Id": 1931,
      "person_id": "student",
      "person_bbox": [
        1850.9,
        1471.3,
        2000.2,
        1692.9
      ],
      "pose_id": "turn aside",
      "action_id": [
        "look blackboard"
      ],
      "gaze_object": {
        "gaze_object_id": "blackboard",
        "gaze_bbox": []
      }
    },
    {
      "image_Id": 1931,
      "person_id": "student",
      "person_bbox": [
        1985.3,
        1407.7,
        2087.4,
        1592.3
      ],
      "pose_id": "turn aside",
      "action_id": [
        "look blackboard"
      ],
      "gaze_object": {
        "gaze_object_id": "blackboard",
        "gaze_bbox": []
      }
    },
    {
      "image_Id": 1931,
      "person_id": "student",
      "person_bbox": [
        2078.8,
        1399,
        2158.9,
        1576.6
      ],
      "pose_id": "turn aside",
      "action_id": [
        "look blackboard"
      ],
      "gaze_object": {
        "gaze_object_id": "blackboard",
        "gaze_bbox": []
      }
    },
    {
      "image_Id": 1931,
      "person_id": "student",
      "person_bbox": [
        2174.6,
        1386.5,
        2254,
        1575
      ],
      "pose_id": "turn aside",
      "action_id": [
        "look blackboard"
      ],
      "gaze_object": {
        "gaze_object_id": "blackboard",
        "gaze_bbox": []
      }
    },
    {
      "image_Id": 1931,
      "person_id": "student",
      "person_bbox": [
        2099,
        1607.9,
        2243.2,
        1884.5
      ],
      "pose_id": "turn aside",
      "action_id": [
        "look blackboard"
      ],
      "gaze_object": {
        "gaze_object_id": "blackboard",
        "gaze_bbox": []
      }
    },
    {
      "image_Id": 1931,
      "person_id": "student",
      "person_bbox": [
        1785.7,
        1641.9,
        2011.7,
        1956.1
      ],
      "pose_id": "turn aside",
      "action_id": [
        "look blackboard"
      ],
      "gaze_object": {
        "gaze_object_id": "blackboard",
        "gaze_bbox": []
      }
    },
    {
      "image_Id": 1931,
      "person_id": "student",
      "person_bbox": [
        1620.3,
        1565.7,
        1756.3,
        1810
      ],
      "pose_id": "turn aside",
      "action_id": [
        "look blackboard"
      ],
      "gaze_object": {
        "gaze_object_id": "blackboard",
        "gaze_bbox": []
      }
    },
    {
      "image_Id": 1931,
      "person_id": "student",
      "person_bbox": [
        1703.9,
        1494.9,
        1866.5,
        1703.5
      ],
      "pose_id": "turn aside",
      "action_id": [
        "look blackboard"
      ],
      "gaze_object": {
        "gaze_object_id": "blackboard",
        "gaze_bbox": []
      }
    },
    {
      "image_Id": 1931,
      "person_id": "student",
      "person_bbox": [
        2261.9,
        1450.2,
        2384.6,
        1620.6
      ],
      "pose_id": "turn aside",
      "action_id": [
        "look blackboard"
      ],
      "gaze_object": {
        "gaze_object_id": "blackboard",
        "gaze_bbox": []
      }
    },
    {
      "image_Id": 1931,
      "person_id": "student",
      "person_bbox": [
        1585.3,
        1433.3,
        1686.1,
        1623.5
      ],
      "pose_id": "turn aside",
      "action_id": [
        "look blackboard"
      ],
      "gaze_object": {
        "gaze_object_id": "blackboard",
        "gaze_bbox": []
      }
    },
    {
      "image_Id": 1931,
      "person_id": "student",
      "person_bbox": [
        790.4,
        1495.8,
        917.3,
        1666.9
      ],
      "pose_id": "lower the head",
      "action_id": [
        "unknown"
      ],
      "gaze_object": {
        "gaze_object_id": "unknown",
        "gaze_bbox": []
      }
    }
  ]
}