{
  "images": {
    "filename": "Video_01_image_image_00034.jpg",
    "image_Id": 254,
    "width": 1920,
    "height": 1080
  },
  "persons": [
    {
      "image_Id": 254,
      "person_id": "student",
      "person_bbox": [
        149.2,
        698.3,
        339,
        973.9
      ],
      "pose_id": "lift the head",
      "action_id": [
        "look blackboard"
      ],
      "gaze_object": {
        "gaze_object_id": "blackboard",
        "gaze_bbox": []
      }
    },
    {
      "image_Id": 254,
      "person_id": "student",
      "person_bbox": [
        387.7,
        642,
        603.8,
        1001.6
      ],
      "pose_id": "lift the head",
      "action_id": [
        "look blackboard"
      ],
      "gaze_object": {
        "gaze_object_id": "blackboard",
        "gaze_bbox": []
      }
    },
    {
      "image_Id": 254,
      "person_id": "student",
      "person_bbox": [
        503.1,
        765.4,
        813.9,
        1080
      ],
      "pose_id": "lift the head",
      "action_id": [
        "distracted"
      ],
      "gaze_object": {
        "gaze_object_id": "other",
        "gaze_bbox": []
      }
    },
    {
      "image_Id": 254,
      "person_id": "student",
      "person_bbox": [
        174.9,
        513.5,
        358.3,
        787.9
      ],
      "pose_id": "turn aside",
      "action_id": [
        "look blackboard"
      ],
      "gaze_object": {
        "gaze_object_id": "blackboard",
        "gaze_bbox": []
      }
    },
    {
      "image_Id": 254,
      "person_id": "student",
      "person_bbox": [
        621.7,
        494.1,
        818.5,
        762.9
      ],
      "pose_id": "lift the head",
      "action_id": [
        "look blackboard"
      ],
      "gaze_object": {
        "gaze_object_id": "blackboard",
        "gaze_bbox": []
      }
    },
    {
      "image_Id": 254,
      "person_id": "student",
      "person_bbox": [
        347.9,
        422.4,
        490.7,
        620.7
      ],
      "pose_id": "lower the head",
      "action_id": [
        "play phone"
      ],
      "gaze_object": {
        "gaze_object_id": "phone",
        "gaze_bbox": [
          423.8,
          579.7,
          448.6,
          613.8
        ]
      }
    },
    {
      "image_Id": 254,
      "person_id": "student",
      "person_bbox": [
        533.8,
        411.8,
        671,
        581.2
      ],
      "pose_id": "turn aside",
      "action_id": [
        "distracted"
      ],
      "gaze_object": {
        "gaze_object_id": "other",
        "gaze_bbox": []
      }
    },
    {
      "image_Id": 254,
      "person_id": "student",
      "person_bbox": [
        765.6,
        398.9,
        870.2,
        649.9
      ],
      "pose_id": "turn aside",
      "action_id": [
        "look blackboard"
      ],
      "gaze_object": {
        "gaze_object_id": "blackboard",
        "gaze_bbox": []
      }
    },
    {
      "image_Id": 254,
      "person_id": "student",
      "person_bbox": [
        677.7,
        340.3,
        776,
        544
      ],
      "pose_id": "lift the head",
      "action_id": [
        "look blackboard"
      ],
      "gaze_object": {
        "gaze_object_id": "blackboard",
        "gaze_bbox": []
      }
    },
    {
      "image_Id": 254,
      "person_id": "student",
      "person_bbox": [
        357.5,
        348.3,
        457.1,
        531.7
      ],
      "pose_id": "turn aside",
      "action_id": [
        "look blackboard"
      ],
      "gaze_object": {
        "gaze_object_id": "blackboard",
        "gaze_bbox": []
      }
    },
    {
      "image_Id": 254,
      "person_id": "student",
      "person_bbox": [
        532.3,
        317,
        639.8,
        432.5
      ],
      "pose_id": "lower the head",
      "action_id": [
        "play phone"
      ],
      "gaze_object": {
        "gaze_object_id": "phone",
        "gaze_bbox": []
      }
    },
    {
      "image_Id": 254,
      "person_id": "student",
      "person_bbox": [
        668.4,
        288.2,
        765.3,
        431.6
      ],
      "pose_id": "lift the head",
      "action_id": [
        "look blackboard"
      ],
      "gaze_object": {
        "gaze_object_id": "blackboard",
        "gaze_bbox": []
      }
    },
    {
      "image_Id": 254,
      "person_id": "student",
      "person_bbox": [
        819.2,
        307.2,
        913.2,
        487.4
      ],
      "pose_id": "turn aside",
      "action_id": [
        "look blackboard"
      ],
      "gaze_object": {
        "gaze_object_id": "blackboard",
        "gaze_bbox": []
      }
    },
    {
      "image_Id": 254,
      "person_id": "student",
      "person_bbox": [
        739.1,
        261.3,
        822.6,
        400.3
      ],
      "pose_id": "lift the head",
      "action_id": [
        "look blackboard"
      ],
      "gaze_object": {
        "gaze_object_id": "blackboard",
        "gaze_bbox": []
      }
    },
    {
      "image_Id": 254,
      "person_id": "student",
      "person_bbox": [
        634.8,
        248.4,
        714.1,
        390
      ],
      "pose_id": "lift the head",
      "action_id": [
        "look blackboard"
      ],
      "gaze_object": {
        "gaze_object_id": "blackboard",
        "gaze_bbox": []
      }
    },
    {
      "image_Id": 254,
      "person_id": "student",
      "person_bbox": [
        664.3,
        226,
        755.5,
        326.8
      ],
      "pose_id": "lift the head",
      "action_id": [
        "look blackboard"
      ],
      "gaze_object": {
        "gaze_object_id": "blackboard",
        "gaze_bbox": []
      }
    },
    {
      "image_Id": 254,
      "person_id": "student",
      "person_bbox": [
        553.7,
        212,
        637.1,
        315.9
      ],
      "pose_id": "lift the head",
      "action_id": [
        "look blackboard"
      ],
      "gaze_object": {
        "gaze_object_id": "blackboard",
        "gaze_bbox": []
      }
    },
    {
      "image_Id": 254,
      "person_id": "student",
      "person_bbox": [
        751.2,
        199.6,
        812.1,
        305.6
      ],
      "pose_id": "turn aside",
      "action_id": [
        "look blackboard"
      ],
      "gaze_object": {
        "gaze_object_id": "blackboard",
        "gaze_bbox": []
      }
    },
    {
      "image_Id": 254,
      "person_id": "student",
      "person_bbox": [
        855.8,
        210.6,
        912.7,
        309
      ],
      "pose_id": "turn aside",
      "action_id": [
        "look student"
      ],
      "gaze_object": {
        "gaze_object_id": "student",
        "gaze_bbox": [
          664.3,
          226,
          755.5,
          326.8
        ]
      }
    },
    {
      "image_Id": 254,
      "person_id": "student",
      "person_bbox": [
        919.2,
        192.8,
        991.1,
        305.1
      ],
      "pose_id": "lift the head",
      "action_id": [
        "look blackboard"
      ],
      "gaze_object": {
        "gaze_object_id": "blackboard",
        "gaze_bbox": []
      }
    },
    {
      "image_Id": 254,
      "person_id": "student",
      "person_bbox": [
        977.4,
        210.6,
        1048.3,
        347.7
      ],
      "pose_id": "turn aside",
      "action_id": [
        "look blackboard"
      ],
      "gaze_object": {
        "gaze_object_id": "blackboard",
        "gaze_bbox": []
      }
    },
    {
      "image_Id": 254,
      "person_id": "student",
      "person_bbox": [
        919,
        235.9,
        1009,
        408.8
      ],
      "pose_id": "turn aside",
      "action_id": [
        "distracted"
      ],
      "gaze_object": {
        "gaze_object_id": "other",
        "gaze_bbox": []
      }
    },
    {
      "image_Id": 254,
      "person_id": "student",
      "person_bbox": [
        835.6,
        245.9,
        933,
        408
      ],
      "pose_id": "lift the head",
      "action_id": [
        "look blackboard"
      ],
      "gaze_object": {
        "gaze_object_id": "blackboard",
        "gaze_bbox": []
      }
    },
    {
      "image_Id": 254,
      "person_id": "student",
      "person_bbox": [
        932.3,
        737.1,
        1152,
        1079.1
      ],
      "pose_id": "turn aside",
      "action_id": [
        "look blackboard"
      ],
      "gaze_object": {
        "gaze_object_id": "blackboard",
        "gaze_bbox": []
      }
    },
    {
      "image_Id": 254,
      "person_id": "student",
      "person_bbox": [
        1134.7,
        622,
        1334.3,
        857
      ],
      "pose_id": "turn aside",
      "action_id": [
        "look blackboard"
      ],
      "gaze_object": {
        "gaze_object_id": "blackboard",
        "gaze_bbox": []
      }
    },
    {
      "image_Id": 254,
      "person_id": "student",
      "person_bbox": [
        1283.9,
        525.6,
        1476.4,
        845.9
      ],
      "pose_id": "turn aside",
      "action_id": [
        "look blackboard"
      ],
      "gaze_object": {
        "gaze_object_id": "blackboard",
        "gaze_bbox": []
      }
    },
    {
      "image_Id": 254,
      "person_id": "student",
      "person_bbox": [
        1653.4,
        714.4,
        1920,
        1080
      ],
      "pose_id": "lift the head",
      "action_id": [
        "look blackboard"
      ],
      "gaze_object": {
        "gaze_object_id": "blackboard",
        "gaze_bbox": []
      }
    },
    {
      "image_Id": 254,
      "person_id": "student",
      "person_bbox": [
        1636.7,
        453.1,
        1788.2,
        730.1
      ],
      "pose_id": "lift the head",
      "action_id": [
        "look blackboard"
      ],
      "gaze_object": {
        "gaze_object_id": "blackboard",
        "gaze_bbox": []
      }
    },
    {
      "image_Id": 254,
      "person_id": "student",
      "person_bbox": [
        1503.3,
        347.9,
        1659.2,
        608.6
      ],
      "pose_id": "turn aside",
      "action_id": [
        "look blackboard"
      ],
      "gaze_object": {
        "gaze_object_id": "blackboard",
        "gaze_bbox": []
      }
    },
    {
      "image_Id": 254,
      "person_id": "student",
      "person_bbox": [
        1337.8,
        332.9,
        1446.7,
        530.9
      ],
      "pose_id": "turn aside",
      "action_id": [
        "look blackboard"
      ],
      "gaze_object": {
        "gaze_object_id": "blackboard",
        "gaze_bbox": []
      }
    },
    {
      "image_Id": 254,
      "person_id": "student",
      "person_bbox": [
        1152.8,
        395.5,
        1292.7,
        556.3
      ],
      "pose_id": "lower the head",
      "action_id": [
        "read"
      ],
      "gaze_object": {
        "gaze_object_id": "book",
        "gaze_bbox": [
          1205.4,
          510.6,
          1314.1,
          556.8
        ]
      }
    },
    {
      "image_Id": 254,
      "person_id": "student",
      "person_bbox": [
        1059.9,
        430.4,
        1200.3,
        637.3
      ],
      "pose_id": "turn aside",
      "action_id": [
        "look blackboard"
      ],
      "gaze_object": {
        "gaze_object_id": "blackboard",
        "gaze_bbox": []
      }
    },
    {
      "image_Id": 254,
      "person_id": "student",
      "person_bbox": [
        1051,
        289,
        1132.4,
        424.1
      ],
      "pose_id": "lift the head",
      "action_id": [
        "photograph"
      ],
      "gaze_object": {
        "gaze_object_id": "phone",
        "gaze_bbox": [
          1086.3,
          337.1,
          1101,
          365.8
        ]
      }
    },
    {
      "image_Id": 254,
      "person_id": "student",
      "person_bbox": [
        1153.1,
        268.1,
        1239.6,
        395.4
      ],
      "pose_id": "turn aside",
      "action_id": [
        "look student"
      ],
      "gaze_object": {
        "gaze_object_id": "student",
        "gaze_bbox": [
          1051,
          289,
          1132.4,
          424.1
        ]
      }
    },
    {
      "image_Id": 254,
      "person_id": "student",
      "person_bbox": [
        1282.6,
        227.8,
        1386.2,
        391.9
      ],
      "pose_id": "lift the head",
      "action_id": [
        "look blackboard"
      ],
      "gaze_object": {
        "gaze_object_id": "blackboard",
        "gaze_bbox": []
      }
    },
    {
      "image_Id": 254,
      "person_id": "student",
      "person_bbox": [
        1427.3,
        275.5,
        1527.1,
        418.8
      ],
      "pose_id": "lift the head",
      "action_id": [
        "look blackboard"
      ],
      "gaze_object": {
        "gaze_object_id": "blackboard",
        "gaze_bbox": []
      }
    },
    {
      "image_Id": 254,
      "person_id": "student",
      "person_bbox": [
        1437.6,
        331.6,
        1540.9,
        498.2
      ],
      "pose_id": "turn aside",
      "action_id": [
        "look blackboard"
      ],
      "gaze_object": {
        "gaze_object_id": "blackboard",
        "gaze_bbox": []
      }
    },
    {
      "image_Id": 254,
      "person_id": "student",
      "person_bbox": [
        1566.7,
        276.8,
        1670,
        439.8
      ],
      "pose_id": "turn aside",
      "action_id": [
        "look blackboard"
      ],
      "gaze_object": {
        "gaze_object_id": "blackboard",
        "gaze_bbox": []
      }
    }
  ]
}